Metadata-Version: 1.0
Name: anybox.recipe.sysdeps
Version: 0.1
Summary: A buildout recipe to check system dependencies
Home-page: https://code.launchpad.net/~anybox/+junk/anybox.recipe.sysdeps
Author: Christophe Combelles
Author-email: ccomb@free.fr
License: ZPL
Platform: UNKNOWN
Classifier: Framework :: Buildout
Classifier: Intended Audience :: Developers
Classifier: Topic :: Software Development :: Build Tools
Classifier: Topic :: Software Development :: Libraries :: Python Modules
